hoopoe.py
international_phone_prefixes.py
us_states.py
hoopoe-0.0.5.dist-info/LICENSE.txt
hoopoe-0.0.5.dist-info/METADATA
hoopoe-0.0.5.dist-info/WHEEL
hoopoe-0.0.5.dist-info/top_level.txt
hoopoe-0.0.5.dist-info/RECORD
