Metadata-Version: 2.1
Name: hoopoe
Version: 0.0.5
Summary: Hoopoe is a data enrichment service that makes it easy to improve your data-centric services and increase the accuracy of your ML models.
Home-page: https://github.com/delbarital/hoopoe
Author: Tal Delbari
Author-email: delbarital@gmail.com
License: UNKNOWN
Platform: UNKNOWN
Classifier: Development Status :: 2 - Pre-Alpha
Classifier: Programming Language :: Python :: 3.8
Classifier: Programming Language :: Python :: 3.7
Classifier: Programming Language :: Python :: 3.6
Classifier: Programming Language :: Python :: 3.5
Classifier: Programming Language :: Python :: 3.4
Classifier: Programming Language :: Python :: 3.3
Classifier: Programming Language :: Python :: 3
Classifier: License :: OSI Approved :: MIT License
Classifier: Operating System :: OS Independent
Requires-Dist: pandas (>=1)
